{
    "configurations": [
        {
            "name": "Linux",
            "includePath": [
                "${workspaceFolder}/**",
                "${workspaceFolder}/src/vendor"
            ],
            "defines": [],
            "compilerPath": "/usr/bin/g++",
            "cStandard": "gnu17",
            "cppStandard": "gnu++14",
            "intelliSenseMode": "linux-gcc-x64",
            "compilerArgs": [
                "-lglfw -lGLU -lGL -lGLEW -Wall"
            ]
        }
    ],
    "version": 4
}